setup.py
rss/__init__.py
rss/proxy.py
rss.egg-info/PKG-INFO
rss.egg-info/SOURCES.txt
rss.egg-info/dependency_links.txt
rss.egg-info/requires.txt
rss.egg-info/top_level.txt