Metadata-Version: 1.0
Name: rss
Version: 0.0.0
Summary: A Python API for controlling redis master and slave via sentinel.
Home-page: UNKNOWN
Author: Aji Liu
Author-email: amigcamel@gmail.com
License: UNKNOWN
Platform: UNKNOWN
